stackhost/__init__.py
stackhost/main.py
stackhost-0.0.1.dist-info/LICENSE
stackhost-0.0.1.dist-info/METADATA
stackhost-0.0.1.dist-info/WHEEL
stackhost-0.0.1.dist-info/top_level.txt
stackhost-0.0.1.dist-info/RECORD
