Metadata-Version: 2.1
Name: stackhost
Version: 0.0.1
Summary: A shared hosting platform for students and developers offering affordable and free plans for testing and deploying projects.
Home-page: https://github.com/ishikki-akabane/stackhost
Author: iShikki
Author-email: ishikkiakabane@gmail.com
License: GNU General Public License v3.0
Keywords: server,docker,kubernet,database,free,code,hosting,development
Classifier: Framework :: AsyncIO
Classifier: Development Status :: 3 - Alpha
Classifier: Intended Audience :: Developers
Classifier: License :: OSI Approved :: MIT License
Classifier: Natural Language :: English
Classifier: Operating System :: OS Independent
Classifier: Programming Language :: Python :: 3.7
Classifier: Programming Language :: Python :: 3.8
Classifier: Programming Language :: Python :: 3.9
Classifier: Programming Language :: Python :: 3.10
Classifier: Topic :: Internet :: WWW/HTTP
Classifier: Topic :: Software Development :: Libraries
Classifier: Topic :: Software Development :: Build Tools
License-File: LICENSE
Requires-Dist: requests
Requires-Dist: asyncio
Requires-Dist: aiohttp
